[
  {
    "rebalance_date": "2024-06-12T00:00:00",
    "market_signal": "risk_on",
    "gross_exposure": 0.96,
    "total_analyzed": 80,
    "analysis_errors": 0,
    "eligible_candidates": 36,
    "selected_count": 8,
    "universe_size": 80,
    "universe_fingerprint": "dbec0ea9a223",
    "one_way_turnover": 0.48,
    "trade_cost": 0.002736,
    "data_degraded": false,
    "data_degraded_reasons": [],
    "factor_coverage": {
      "revenue_momentum": 0.694,
      "institutional_flow": 0.0
    },
    "eligible_list": [
      "6442",
      "2486",
      "2383",
      "2467",
      "2367",
      "4967",
      "8210",
      "2330",
      "3450",
      "2317",
      "3017",
      "2382",
      "1560",
      "8996",
      "2454",
      "3533",
      "3653",
      "6669",
      "2891",
      "2357",
      "6451",
      "2360",
      "6257",
      "6919",
      "2345",
      "8039",
      "6213",
      "6285",
      "2327",
      "6515",
      "3665",
      "3711",
      "4906",
      "4958",
      "2303",
      "2308"
    ],
    "rejected_not_selected": [
      "3450",
      "2317",
      "3017",
      "2382",
      "1560",
      "8996",
      "2454",
      "3533",
      "3653",
      "6669",
      "2891",
      "2357",
      "6451",
      "2360",
      "6257",
      "6919",
      "2345",
      "8039",
      "6213",
      "6285",
      "2327",
      "6515",
      "3665",
      "3711",
      "4906",
      "4958",
      "2303",
      "2308"
    ],
    "rejected_by_top_n": [
      "3450",
      "2317",
      "3017",
      "2382",
      "1560",
      "8996",
      "2454",
      "3533",
      "3653",
      "6669",
      "2891",
      "2357",
      "6451",
      "2360",
      "6257",
      "6919",
      "2345",
      "8039",
      "6213",
      "6285",
      "2327",
      "6515",
      "3665",
      "3711",
      "4906",
      "4958",
      "2303",
      "2308"
    ],
    "rejected_by_turnover": [
      "2485",
      "8021",
      "3167",
      "6830",
      "1309",
      "2426"
    ],
    "rejected_by_price": [
      "2409",
      "3481",
      "1309",
      "2489",
      "2426",
      "1802"
    ],
    "rejected_by_history": [
      "7769",
      "7822"
    ],
    "rejected_by_trend": [
      "2313",
      "3037",
      "2344",
      "2408",
      "8046",
      "1303",
      "2409",
      "2368",
      "6770",
      "3715",
      "2481",
      "2455",
      "3481",
      "2485",
      "3661",
      "2449",
      "3189",
      "3167",
      "3714",
      "3006",
      "6830",
      "6239",
      "3231",
      "3443",
      "1309",
      "2337",
      "6805",
      "2426",
      "1802",
      "3563",
      "2355",
      "8271",
      "2404",
      "2059",
      "1717",
      "6531",
      "6139",
      "6781",
      "1326",
      "2027"
    ],
    "rejected_by_industry": [],
    "positions": [
      {
        "symbol": "6442",
        "weight": 0.12,
        "score": 86.94,
        "industry": "通信網路業"
      },
      {
        "symbol": "2486",
        "weight": 0.12,
        "score": 77.39,
        "industry": "電子工業"
      },
      {
        "symbol": "2383",
        "weight": 0.12,
        "score": 76.92,
        "industry": "電子零組件業"
      },
      {
        "symbol": "2467",
        "weight": 0.12,
        "score": 76.67,
        "industry": "電子零組件業"
      },
      {
        "symbol": "2367",
        "weight": 0.12,
        "score": 75.19,
        "industry": "電子零組件業"
      },
      {
        "symbol": "4967",
        "weight": 0.12,
        "score": 74.72,
        "industry": "電子工業"
      },
      {
        "symbol": "8210",
        "weight": 0.12,
        "score": 70.75,
        "industry": "電腦及週邊設備業"
      },
      {
        "symbol": "2330",
        "weight": 0.12,
        "score": 67.58,
        "industry": "電子工業"
      }
    ],
    "theme_concentration": {
      "tech_weight": 0.96,
      "tech_count": 8,
      "total_positions": 8,
      "top_industry": "電子工業",
      "top_industry_weight": 0.36,
      "industries": {
        "電子工業": 0.36,
        "電子零組件業": 0.36,
        "通信網路業": 0.12,
        "電腦及週邊設備業": 0.12
      }
    },
    "factor_detail": [
      {
        "symbol": "6442",
        "rank": 1,
        "portfolio_score": 86.94,
        "rank_components": {
          "price_momentum": 100.0,
          "trend_quality": 97.22,
          "revenue_momentum": 50.0
        },
        "price_momentum_raw": 2.1333062036160633,
        "trend_quality_raw": 1.0,
        "revenue_raw": null,
        "institutional_raw": 0.0,
        "industry": "通信網路業"
      },
      {
        "symbol": "2486",
        "rank": 2,
        "portfolio_score": 77.39,
        "rank_components": {
          "price_momentum": 94.44,
          "trend_quality": 97.22,
          "revenue_momentum": 24.0
        },
        "price_momentum_raw": 1.5170849077213313,
        "trend_quality_raw": 1.0,
        "revenue_raw": 0.045857946747287305,
        "institutional_raw": 0.0,
        "industry": "電子工業"
      },
      {
        "symbol": "2383",
        "rank": 3,
        "portfolio_score": 76.92,
        "rank_components": {
          "price_momentum": 75.0,
          "trend_quality": 58.33,
          "revenue_momentum": 96.0
        },
        "price_momentum_raw": 0.7331809473372689,
        "trend_quality_raw": 0.6197,
        "revenue_raw": 0.5740212765004951,
        "institutional_raw": 0.0,
        "industry": "電子零組件業"
      },
      {
        "symbol": "2467",
        "rank": 4,
        "portfolio_score": 76.67,
        "rank_components": {
          "price_momentum": 88.89,
          "trend_quality": 13.89,
          "revenue_momentum": 100.0
        },
        "price_momentum_raw": 1.1984319992917558,
        "trend_quality_raw": 0.3626,
        "revenue_raw": 0.8839352742713276,
        "institutional_raw": 0.0,
        "industry": "電子零組件業"
      },
      {
        "symbol": "2367",
        "rank": 5,
        "portfolio_score": 75.19,
        "rank_components": {
          "price_momentum": 69.44,
          "trend_quality": 75.0,
          "revenue_momentum": 88.0
        },
        "price_momentum_raw": 0.6818799521506317,
        "trend_quality_raw": 0.7565,
        "revenue_raw": 0.37129698090375596,
        "institutional_raw": 0.0,
        "industry": "電子零組件業"
      },
      {
        "symbol": "4967",
        "rank": 6,
        "portfolio_score": 74.72,
        "rank_components": {
          "price_momentum": 77.78,
          "trend_quality": 97.22,
          "revenue_momentum": 50.0
        },
        "price_momentum_raw": 0.7665014357316727,
        "trend_quality_raw": 1.0,
        "revenue_raw": null,
        "institutional_raw": 0.0,
        "industry": "電子工業"
      },
      {
        "symbol": "8210",
        "rank": 7,
        "portfolio_score": 70.75,
        "rank_components": {
          "price_momentum": 91.67,
          "trend_quality": 41.67,
          "revenue_momentum": 48.0
        },
        "price_momentum_raw": 1.275307158119658,
        "trend_quality_raw": 0.5201,
        "revenue_raw": 0.10917786113464728,
        "institutional_raw": 0.0,
        "industry": "電腦及週邊設備業"
      },
      {
        "symbol": "2330",
        "rank": 8,
        "portfolio_score": 67.58,
        "rank_components": {
          "price_momentum": 52.78,
          "trend_quality": 77.78,
          "revenue_momentum": 92.0
        },
        "price_momentum_raw": 0.5228866430373822,
        "trend_quality_raw": 0.7599,
        "revenue_raw": 0.4244806765724614,
        "institutional_raw": 0.0,
        "industry": "電子工業"
      },
      {
        "symbol": "3450",
        "rank": 9,
        "portfolio_score": 67.22,
        "rank_components": {
          "price_momentum": 55.56,
          "trend_quality": 83.33,
          "revenue_momentum": 80.0
        },
        "price_momentum_raw": 0.5808550403016701,
        "trend_quality_raw": 0.7881,
        "revenue_raw": 0.2829545398528642,
        "institutional_raw": 0.0,
        "industry": "電子工業"
      },
      {
        "symbol": "2317",
        "rank": 10,
        "portfolio_score": 66.83,
        "rank_components": {
          "price_momentum": 72.22,
          "trend_quality": 80.56,
          "revenue_momentum": 44.0
        },
        "price_momentum_raw": 0.7189217837826842,
        "trend_quality_raw": 0.7647,
        "revenue_raw": 0.07413980441448798,
        "institutional_raw": 0.0,
        "industry": "電子工業"
      },
      {
        "symbol": "3017",
        "rank": 11,
        "portfolio_score": 64.69,
        "rank_components": {
          "price_momentum": 97.22,
          "trend_quality": 36.11,
          "revenue_momentum": 16.0
        },
        "price_momentum_raw": 1.8056032856032858,
        "trend_quality_raw": 0.4976,
        "revenue_raw": 0.01775475865202629,
        "institutional_raw": 0.0,
        "industry": "電子工業"
      },
      {
        "symbol": "2382",
        "rank": 12,
        "portfolio_score": 64.47,
        "rank_components": {
          "price_momentum": 86.11,
          "trend_quality": 5.56,
          "revenue_momentum": 64.0
        },
        "price_momentum_raw": 1.1313252553841173,
        "trend_quality_raw": 0.2713,
        "revenue_raw": 0.19080703398519486,
        "institutional_raw": 0.0,
        "industry": "電腦及週邊設備業"
      },
      {
        "symbol": "1560",
        "rank": 13,
        "portfolio_score": 61.31,
        "rank_components": {
          "price_momentum": 80.56,
          "trend_quality": 50.0,
          "revenue_momentum": 28.0
        },
        "price_momentum_raw": 0.7845677928952012,
        "trend_quality_raw": 0.5795,
        "revenue_raw": 0.04773766896174221,
        "institutional_raw": 0.0,
        "industry": "電機機械"
      },
      {
        "symbol": "8996",
        "rank": 14,
        "portfolio_score": 60.72,
        "rank_components": {
          "price_momentum": 83.33,
          "trend_quality": 69.44,
          "revenue_momentum": 4.0
        },
        "price_momentum_raw": 0.9434811818611367,
        "trend_quality_raw": 0.7141,
        "revenue_raw": -0.12803943307132418,
        "institutional_raw": 0.0,
        "industry": "電機機械"
      },
      {
        "symbol": "2454",
        "rank": 15,
        "portfolio_score": 60.31,
        "rank_components": {
          "price_momentum": 47.22,
          "trend_quality": 66.67,
          "revenue_momentum": 84.0
        },
        "price_momentum_raw": 0.4482376576361539,
        "trend_quality_raw": 0.6673,
        "revenue_raw": 0.33714673180403376,
        "institutional_raw": 0.0,
        "industry": "電子工業"
      },
      {
        "symbol": "3533",
        "rank": 16,
        "portfolio_score": 58.39,
        "rank_components": {
          "price_momentum": 61.11,
          "trend_quality": 38.89,
          "revenue_momentum": 68.0
        },
        "price_momentum_raw": 0.639721708655222,
        "trend_quality_raw": 0.5045,
        "revenue_raw": 0.21208620125517313,
        "institutional_raw": 0.0,
        "industry": "電子零組件業"
      },
      {
        "symbol": "3653",
        "rank": 17,
        "portfolio_score": 56.78,
        "rank_components": {
          "price_momentum": 66.67,
          "trend_quality": 30.56,
          "revenue_momentum": 56.0
        },
        "price_momentum_raw": 0.6786477810497418,
        "trend_quality_raw": 0.491,
        "revenue_raw": 0.1463882756012164,
        "institutional_raw": 0.0,
        "industry": "電子零組件業"
      },
      {
        "symbol": "6669",
        "rank": 18,
        "portfolio_score": 53.19,
        "rank_components": {
          "price_momentum": 63.89,
          "trend_quality": 27.78,
          "revenue_momentum": 50.0
        },
        "price_momentum_raw": 0.6550935409170386,
        "trend_quality_raw": 0.4821,
        "revenue_raw": null,
        "institutional_raw": 0.0,
        "industry": "電腦及週邊設備業"
      },
      {
        "symbol": "2891",
        "rank": 19,
        "portfolio_score": 51.39,
        "rank_components": {
          "price_momentum": 50.0,
          "trend_quality": 44.44,
          "revenue_momentum": 60.0
        },
        "price_momentum_raw": 0.4493355410107026,
        "trend_quality_raw": 0.55,
        "revenue_raw": 0.16052448431813712,
        "institutional_raw": 0.0,
        "industry": "金融保險"
      },
      {
        "symbol": "2357",
        "rank": 20,
        "portfolio_score": 50.11,
        "rank_components": {
          "price_momentum": 44.44,
          "trend_quality": 33.33,
          "revenue_momentum": 76.0
        },
        "price_momentum_raw": 0.3861247914543729,
        "trend_quality_raw": 0.492,
        "revenue_raw": 0.2586990066749995,
        "institutional_raw": 0.0,
        "industry": "電腦及週邊設備業"
      }
    ],
    "config_hash": "3bb0d8efab1de820",
    "score_dispersion": {
      "std": 19.3316,
      "iqr": 28.1425,
      "n_eligible": 36
    }
  },
  {
    "rebalance_date": "2024-07-12T00:00:00",
    "market_signal": "risk_on",
    "gross_exposure": 0.96,
    "total_analyzed": 80,
    "analysis_errors": 0,
    "eligible_candidates": 43,
    "selected_count": 8,
    "universe_size": 80,
    "universe_fingerprint": "dbec0ea9a223",
    "one_way_turnover": 0.36,
    "trade_cost": 0.002052,
    "data_degraded": false,
    "data_degraded_reasons": [],
    "factor_coverage": {
      "revenue_momentum": 0.721,
      "institutional_flow": 0.0
    },
    "eligible_list": [
      "3450",
      "2467",
      "6442",
      "2486",
      "2489",
      "2382",
      "2059",
      "3653",
      "1560",
      "4967",
      "2367",
      "6451",
      "2383",
      "2317",
      "2330",
      "6919",
      "3017",
      "3533",
      "2345",
      "2360",
      "6239",
      "2454",
      "2449",
      "2313",
      "8996",
      "8039",
      "2891",
      "2455",
      "3167",
      "6213",
      "2327",
      "4958",
      "3665",
      "3711",
      "6257",
      "2357",
      "2308",
      "4906",
      "8021",
      "6515",
      "3189",
      "3006",
      "1717"
    ],
    "rejected_not_selected": [
      "2489",
      "3653",
      "1560",
      "6451",
      "2383",
      "2317",
      "2330",
      "6919",
      "3017",
      "3533",
      "2345",
      "2360",
      "6239",
      "2454",
      "2449",
      "2313",
      "8996",
      "8039",
      "2891",
      "2455",
      "3167",
      "6213",
      "2327",
      "4958",
      "3665",
      "3711",
      "6257",
      "2357",
      "2308",
      "4906",
      "8021",
      "6515",
      "3189",
      "3006",
      "1717"
    ],
    "rejected_by_top_n": [
      "1560",
      "6451",
      "2383",
      "2317",
      "2330",
      "6919",
      "3017",
      "3533",
      "2345",
      "2360",
      "6239",
      "2454",
      "2449",
      "2313",
      "8996",
      "8039",
      "2891",
      "2455",
      "3167",
      "6213",
      "2327",
      "4958",
      "3665",
      "3711",
      "6257",
      "2357",
      "2308",
      "4906",
      "8021",
      "6515",
      "3189",
      "3006",
      "1717"
    ],
    "rejected_by_turnover": [
      "2485",
      "6830",
      "2426"
    ],
    "rejected_by_price": [
      "2409",
      "3481",
      "1309",
      "2426",
      "1802"
    ],
    "rejected_by_history": [
      "7769",
      "7822"
    ],
    "rejected_by_trend": [
      "3037",
      "2344",
      "2408",
      "8046",
      "2303",
      "6285",
      "1303",
      "2368",
      "6770",
      "3715",
      "2481",
      "2485",
      "3661",
      "3714",
      "6669",
      "8210",
      "6830",
      "3231",
      "3443",
      "2337",
      "6805",
      "1802",
      "3563",
      "2355",
      "8271",
      "2404",
      "6531",
      "6139",
      "6781",
      "1326",
      "2027"
    ],
    "rejected_by_industry": [],
    "positions": [
      {
        "symbol": "3450",
        "weight": 0.12,
        "score": 90.6,
        "industry": "電子工業"
      },
      {
        "symbol": "2467",
        "weight": 0.12,
        "score": 89.01,
        "industry": "電子零組件業"
      },
      {
        "symbol": "6442",
        "weight": 0.12,
        "score": 86.8,
        "industry": "通信網路業"
      },
      {
        "symbol": "2486",
        "weight": 0.12,
        "score": 78.87,
        "industry": "電子工業"
      },
      {
        "symbol": "2382",
        "weight": 0.12,
        "score": 73.79,
        "industry": "電腦及週邊設備業"
      },
      {
        "symbol": "2059",
        "weight": 0.12,
        "score": 73.02,
        "industry": "電子零組件業"
      },
      {
        "symbol": "4967",
        "weight": 0.12,
        "score": 67.62,
        "industry": "電子工業"
      },
      {
        "symbol": "2367",
        "weight": 0.12,
        "score": 66.7,
        "industry": "電子零組件業"
      }
    ],
    "theme_concentration": {
      "tech_weight": 0.96,
      "tech_count": 8,
      "total_positions": 8,
      "top_industry": "電子工業",
      "top_industry_weight": 0.36,
      "industries": {
        "電子工業": 0.36,
        "電子零組件業": 0.36,
        "通信網路業": 0.12,
        "電腦及週邊設備業": 0.12
      }
    },
    "factor_detail": [
      {
        "symbol": "3450",
        "rank": 1,
        "portfolio_score": 90.6,
        "rank_components": {
          "price_momentum": 90.7,
          "trend_quality": 90.7,
          "revenue_momentum": 90.32
        },
        "price_momentum_raw": 1.2683552606661772,
        "trend_quality_raw": 0.9939,
        "revenue_raw": 0.34873758920687975,
        "institutional_raw": 0.0,
        "industry": "電子工業"
      },
      {
        "symbol": "2467",
        "rank": 2,
        "portfolio_score": 89.01,
        "rank_components": {
          "price_momentum": 93.02,
          "trend_quality": 96.51,
          "revenue_momentum": 74.19
        },
        "price_momentum_raw": 1.4834911380612081,
        "trend_quality_raw": 1.0,
        "revenue_raw": 0.30590051727554995,
        "institutional_raw": 0.0,
        "industry": "電子零組件業"
      },
      {
        "symbol": "6442",
        "rank": 3,
        "portfolio_score": 86.8,
        "rank_components": {
          "price_momentum": 100.0,
          "trend_quality": 96.51,
          "revenue_momentum": 50.0
        },
        "price_momentum_raw": 4.248335086847947,
        "trend_quality_raw": 1.0,
        "revenue_raw": null,
        "institutional_raw": 0.0,
        "industry": "通信網路業"
      },
      {
        "symbol": "2486",
        "rank": 4,
        "portfolio_score": 78.87,
        "rank_components": {
          "price_momentum": 97.67,
          "trend_quality": 81.4,
          "revenue_momentum": 35.48
        },
        "price_momentum_raw": 2.13567242114237,
        "trend_quality_raw": 0.9537,
        "revenue_raw": 0.15505066233685807,
        "institutional_raw": 0.0,
        "industry": "電子工業"
      },
      {
        "symbol": "2489",
        "rank": 5,
        "portfolio_score": 77.84,
        "rank_components": {
          "price_momentum": 69.77,
          "trend_quality": 96.51,
          "revenue_momentum": 80.65
        },
        "price_momentum_raw": 0.6829213594865768,
        "trend_quality_raw": 1.0,
        "revenue_raw": 0.3156782331322772,
        "institutional_raw": 0.0,
        "industry": "電子工業"
      },
      {
        "symbol": "2382",
        "rank": 6,
        "portfolio_score": 73.79,
        "rank_components": {
          "price_momentum": 79.07,
          "trend_quality": 62.79,
          "revenue_momentum": 70.97
        },
        "price_momentum_raw": 0.8707636841520234,
        "trend_quality_raw": 0.8385,
        "revenue_raw": 0.2809825651833051,
        "institutional_raw": 0.0,
        "industry": "電腦及週邊設備業"
      },
      {
        "symbol": "2059",
        "rank": 7,
        "portfolio_score": 73.02,
        "rank_components": {
          "price_momentum": 81.4,
          "trend_quality": 16.28,
          "revenue_momentum": 100.0
        },
        "price_momentum_raw": 0.9711921852497091,
        "trend_quality_raw": 0.4815,
        "revenue_raw": 0.7616610274418487,
        "institutional_raw": 0.0,
        "industry": "電子零組件業"
      },
      {
        "symbol": "3653",
        "rank": 8,
        "portfolio_score": 69.3,
        "rank_components": {
          "price_momentum": 67.44,
          "trend_quality": 96.51,
          "revenue_momentum": 51.61
        },
        "price_momentum_raw": 0.6718065668486234,
        "trend_quality_raw": 1.0,
        "revenue_raw": 0.21935625192837394,
        "institutional_raw": 0.0,
        "industry": "電子零組件業"
      },
      {
        "symbol": "1560",
        "rank": 9,
        "portfolio_score": 69.13,
        "rank_components": {
          "price_momentum": 86.05,
          "trend_quality": 76.74,
          "revenue_momentum": 25.81
        },
        "price_momentum_raw": 1.0813383774345005,
        "trend_quality_raw": 0.9379,
        "revenue_raw": 0.11464363928002191,
        "institutional_raw": 0.0,
        "industry": "電機機械"
      },
      {
        "symbol": "4967",
        "rank": 10,
        "portfolio_score": 67.62,
        "rank_components": {
          "price_momentum": 88.37,
          "trend_quality": 32.56,
          "revenue_momentum": 50.0
        },
        "price_momentum_raw": 1.1414895215809733,
        "trend_quality_raw": 0.6449,
        "revenue_raw": null,
        "institutional_raw": 0.0,
        "industry": "電子工業"
      },
      {
        "symbol": "2367",
        "rank": 11,
        "portfolio_score": 66.7,
        "rank_components": {
          "price_momentum": 74.42,
          "trend_quality": 44.19,
          "revenue_momentum": 67.74
        },
        "price_momentum_raw": 0.8518155626451659,
        "trend_quality_raw": 0.7593,
        "revenue_raw": 0.2668979041957779,
        "institutional_raw": 0.0,
        "industry": "電子零組件業"
      },
      {
        "symbol": "6451",
        "rank": 12,
        "portfolio_score": 66.45,
        "rank_components": {
          "price_momentum": 83.72,
          "trend_quality": 39.53,
          "revenue_momentum": 50.0
        },
        "price_momentum_raw": 1.0104933793165471,
        "trend_quality_raw": 0.7354,
        "revenue_raw": null,
        "institutional_raw": 0.0,
        "industry": "半導體業"
      },
      {
        "symbol": "2383",
        "rank": 13,
        "portfolio_score": 66.18,
        "rank_components": {
          "price_momentum": 65.12,
          "trend_quality": 34.88,
          "revenue_momentum": 93.55
        },
        "price_momentum_raw": 0.6461990896268405,
        "trend_quality_raw": 0.6625,
        "revenue_raw": 0.49730105871237235,
        "institutional_raw": 0.0,
        "industry": "電子零組件業"
      },
      {
        "symbol": "2317",
        "rank": 14,
        "portfolio_score": 64.43,
        "rank_components": {
          "price_momentum": 72.09,
          "trend_quality": 67.44,
          "revenue_momentum": 45.16
        },
        "price_momentum_raw": 0.8183107950025735,
        "trend_quality_raw": 0.8711,
        "revenue_raw": 0.19349653744167086,
        "institutional_raw": 0.0,
        "industry": "電子工業"
      },
      {
        "symbol": "2330",
        "rank": 15,
        "portfolio_score": 64.27,
        "rank_components": {
          "price_momentum": 60.47,
          "trend_quality": 74.42,
          "revenue_momentum": 64.52
        },
        "price_momentum_raw": 0.609235754119059,
        "trend_quality_raw": 0.9201,
        "revenue_raw": 0.2560368107166091,
        "institutional_raw": 0.0,
        "industry": "電子工業"
      },
      {
        "symbol": "6919",
        "rank": 16,
        "portfolio_score": 57.5,
        "rank_components": {
          "price_momentum": 58.14,
          "trend_quality": 65.12,
          "revenue_momentum": 50.0
        },
        "price_momentum_raw": 0.5961988695797261,
        "trend_quality_raw": 0.8449,
        "revenue_raw": null,
        "institutional_raw": 0.0,
        "industry": "化學生技醫療"
      },
      {
        "symbol": "3017",
        "rank": 17,
        "portfolio_score": 57.4,
        "rank_components": {
          "price_momentum": 95.35,
          "trend_quality": 4.65,
          "revenue_momentum": 16.13
        },
        "price_momentum_raw": 1.6011854332564555,
        "trend_quality_raw": 0.3119,
        "revenue_raw": 0.035689741038256347,
        "institutional_raw": 0.0,
        "industry": "電子工業"
      },
      {
        "symbol": "3533",
        "rank": 18,
        "portfolio_score": 56.22,
        "rank_components": {
          "price_momentum": 62.79,
          "trend_quality": 11.63,
          "revenue_momentum": 77.42
        },
        "price_momentum_raw": 0.6120470537528935,
        "trend_quality_raw": 0.3805,
        "revenue_raw": 0.3126852622297753,
        "institutional_raw": 0.0,
        "industry": "電子零組件業"
      },
      {
        "symbol": "2345",
        "rank": 19,
        "portfolio_score": 54.34,
        "rank_components": {
          "price_momentum": 39.53,
          "trend_quality": 58.14,
          "revenue_momentum": 83.87
        },
        "price_momentum_raw": 0.3476127672263656,
        "trend_quality_raw": 0.8152,
        "revenue_raw": 0.31576116005637284,
        "institutional_raw": 0.0,
        "industry": "電子工業"
      },
      {
        "symbol": "2360",
        "rank": 20,
        "portfolio_score": 50.26,
        "rank_components": {
          "price_momentum": 34.88,
          "trend_quality": 46.51,
          "revenue_momentum": 87.1
        },
        "price_momentum_raw": 0.31705296930052557,
        "trend_quality_raw": 0.7661,
        "revenue_raw": 0.34823549669616505,
        "institutional_raw": 0.0,
        "industry": "其他電子業"
      }
    ],
    "config_hash": "3bb0d8efab1de820",
    "score_dispersion": {
      "std": 19.4497,
      "iqr": 31.095,
      "n_eligible": 43
    }
  },
  {
    "rebalance_date": "2024-08-12T00:00:00",
    "market_signal": "risk_off",
    "gross_exposure": 0.35,
    "total_analyzed": 80,
    "analysis_errors": 0,
    "eligible_candidates": 52,
    "selected_count": 8,
    "universe_size": 80,
    "universe_fingerprint": "dbec0ea9a223",
    "one_way_turnover": 0.47,
    "trade_cost": 0.002679,
    "data_degraded": false,
    "data_degraded_reasons": [],
    "factor_coverage": {
      "revenue_momentum": 0.75,
      "institutional_flow": 0.0
    },
    "eligible_list": [
      "2467",
      "3450",
      "6442",
      "6919",
      "3167",
      "6139",
      "2489",
      "1560",
      "2486",
      "6805",
      "2330",
      "3653",
      "2383",
      "2449",
      "2317",
      "3533",
      "3017",
      "2367",
      "8210",
      "2382",
      "2059",
      "4967",
      "2327",
      "3665",
      "2357",
      "2368",
      "2313",
      "2454",
      "4906",
      "4958",
      "6515",
      "2360",
      "2345",
      "2308",
      "2455",
      "8021",
      "3189",
      "2404",
      "2891",
      "3563",
      "2303",
      "8039",
      "3711",
      "6257",
      "2355",
      "3231",
      "6830",
      "2337",
      "1717",
      "3714",
      "3037",
      "2027"
    ],
    "rejected_not_selected": [
      "1560",
      "6805",
      "2330",
      "3653",
      "2383",
      "2449",
      "2317",
      "3533",
      "3017",
      "2367",
      "8210",
      "2382",
      "2059",
      "4967",
      "2327",
      "3665",
      "2357",
      "2368",
      "2313",
      "2454",
      "4906",
      "4958",
      "6515",
      "2360",
      "2345",
      "2308",
      "2455",
      "8021",
      "3189",
      "2404",
      "2891",
      "3563",
      "2303",
      "8039",
      "3711",
      "6257",
      "2355",
      "3231",
      "6830",
      "2337",
      "1717",
      "3714",
      "3037",
      "2027"
    ],
    "rejected_by_top_n": [
      "6805",
      "2330",
      "3653",
      "2383",
      "2449",
      "2317",
      "3533",
      "3017",
      "2367",
      "8210",
      "2382",
      "2059",
      "4967",
      "2327",
      "3665",
      "2357",
      "2368",
      "2313",
      "2454",
      "4906",
      "4958",
      "6515",
      "2360",
      "2345",
      "2308",
      "2455",
      "8021",
      "3189",
      "2404",
      "2891",
      "3563",
      "2303",
      "8039",
      "3711",
      "6257",
      "2355",
      "3231",
      "6830",
      "2337",
      "1717",
      "3714",
      "3037",
      "2027"
    ],
    "rejected_by_turnover": [
      "2485",
      "2426",
      "8271"
    ],
    "rejected_by_price": [
      "2409",
      "3481",
      "2485",
      "1309",
      "2426",
      "1802"
    ],
    "rejected_by_history": [
      "7769",
      "7822"
    ],
    "rejected_by_trend": [
      "2344",
      "2408",
      "8046",
      "6285",
      "1303",
      "2409",
      "6770",
      "3715",
      "6213",
      "2481",
      "2485",
      "3661",
      "6669",
      "8996",
      "3006",
      "6451",
      "6239",
      "3443",
      "8271",
      "6531",
      "6781",
      "1326"
    ],
    "rejected_by_industry": [],
    "positions": [
      {
        "symbol": "2467",
        "weight": 0.0517,
        "score": 96.25,
        "industry": "電子零組件業"
      },
      {
        "symbol": "3450",
        "weight": 0.0489,
        "score": 91.09,
        "industry": "電子工業"
      },
      {
        "symbol": "6442",
        "weight": 0.0464,
        "score": 86.35,
        "industry": "通信網路業"
      },
      {
        "symbol": "6919",
        "weight": 0.0415,
        "score": 77.21,
        "industry": "化學生技醫療"
      },
      {
        "symbol": "3167",
        "weight": 0.0415,
        "score": 77.15,
        "industry": "電機機械"
      },
      {
        "symbol": "6139",
        "weight": 0.0414,
        "score": 77.02,
        "industry": "其他電子業"
      },
      {
        "symbol": "2489",
        "weight": 0.0406,
        "score": 75.58,
        "industry": "電子工業"
      },
      {
        "symbol": "2486",
        "weight": 0.038,
        "score": 70.77,
        "industry": "電子工業"
      }
    ],
    "theme_concentration": {
      "tech_weight": 0.3085,
      "tech_count": 7,
      "total_positions": 8,
      "top_industry": "電子工業",
      "top_industry_weight": 0.1275,
      "industries": {
        "電子工業": 0.1275,
        "電子零組件業": 0.0517,
        "通信網路業": 0.0464,
        "化學生技醫療": 0.0415,
        "電機機械": 0.0415,
        "其他電子業": 0.0414
      }
    },
    "factor_detail": [
      {
        "symbol": "2467",
        "rank": 1,
        "portfolio_score": 96.25,
        "rank_components": {
          "price_momentum": 98.08,
          "trend_quality": 86.54,
          "revenue_momentum": 100.0
        },
        "price_momentum_raw": 1.903201432831435,
        "trend_quality_raw": 0.4525,
        "revenue_raw": 0.9282870889979614,
        "institutional_raw": 0.0,
        "industry": "電子零組件業"
      },
      {
        "symbol": "3450",
        "rank": 2,
        "portfolio_score": 91.09,
        "rank_components": {
          "price_momentum": 96.15,
          "trend_quality": 98.08,
          "revenue_momentum": 74.36
        },
        "price_momentum_raw": 1.8012448257284286,
        "trend_quality_raw": 0.6288,
        "revenue_raw": 0.25143972996128167,
        "institutional_raw": 0.0,
        "industry": "電子工業"
      },
      {
        "symbol": "6442",
        "rank": 3,
        "portfolio_score": 86.35,
        "rank_components": {
          "price_momentum": 100.0,
          "trend_quality": 94.23,
          "revenue_momentum": 50.0
        },
        "price_momentum_raw": 4.712276931885113,
        "trend_quality_raw": 0.6031,
        "revenue_raw": null,
        "institutional_raw": 0.0,
        "industry": "通信網路業"
      },
      {
        "symbol": "6919",
        "rank": 4,
        "portfolio_score": 77.21,
        "rank_components": {
          "price_momentum": 82.69,
          "trend_quality": 96.15,
          "revenue_momentum": 50.0
        },
        "price_momentum_raw": 0.8158037582136175,
        "trend_quality_raw": 0.6068,
        "revenue_raw": null,
        "institutional_raw": 0.0,
        "industry": "化學生技醫療"
      },
      {
        "symbol": "3167",
        "rank": 5,
        "portfolio_score": 77.15,
        "rank_components": {
          "price_momentum": 59.62,
          "trend_quality": 100.0,
          "revenue_momentum": 97.44
        },
        "price_momentum_raw": 0.525338428586036,
        "trend_quality_raw": 0.778,
        "revenue_raw": 0.8283612324171089,
        "institutional_raw": 0.0,
        "industry": "電機機械"
      },
      {
        "symbol": "6139",
        "rank": 6,
        "portfolio_score": 77.02,
        "rank_components": {
          "price_momentum": 94.23,
          "trend_quality": 63.46,
          "revenue_momentum": 50.0
        },
        "price_momentum_raw": 1.597743648198698,
        "trend_quality_raw": 0.2328,
        "revenue_raw": null,
        "institutional_raw": 0.0,
        "industry": "其他電子業"
      },
      {
        "symbol": "2489",
        "rank": 7,
        "portfolio_score": 75.58,
        "rank_components": {
          "price_momentum": 65.38,
          "trend_quality": 82.69,
          "revenue_momentum": 92.31
        },
        "price_momentum_raw": 0.5520598621838024,
        "trend_quality_raw": 0.4358,
        "revenue_raw": 0.5932768018608346,
        "institutional_raw": 0.0,
        "industry": "電子工業"
      },
      {
        "symbol": "1560",
        "rank": 8,
        "portfolio_score": 71.22,
        "rank_components": {
          "price_momentum": 88.46,
          "trend_quality": 61.54,
          "revenue_momentum": 41.03
        },
        "price_momentum_raw": 1.044016011780206,
        "trend_quality_raw": 0.2263,
        "revenue_raw": 0.09936824198782332,
        "institutional_raw": 0.0,
        "industry": "電機機械"
      },
      {
        "symbol": "2486",
        "rank": 9,
        "portfolio_score": 70.77,
        "rank_components": {
          "price_momentum": 92.31,
          "trend_quality": 51.92,
          "revenue_momentum": 38.46
        },
        "price_momentum_raw": 1.3690889072391963,
        "trend_quality_raw": 0.1648,
        "revenue_raw": 0.09702950905496259,
        "institutional_raw": 0.0,
        "industry": "電子工業"
      },
      {
        "symbol": "6805",
        "rank": 10,
        "portfolio_score": 70.67,
        "rank_components": {
          "price_momentum": 90.38,
          "trend_quality": 42.31,
          "revenue_momentum": 50.0
        },
        "price_momentum_raw": 1.147571465823743,
        "trend_quality_raw": 0.1051,
        "revenue_raw": null,
        "institutional_raw": 0.0,
        "industry": "電子零組件業"
      },
      {
        "symbol": "2330",
        "rank": 11,
        "portfolio_score": 69.71,
        "rank_components": {
          "price_momentum": 67.31,
          "trend_quality": 67.31,
          "revenue_momentum": 76.92
        },
        "price_momentum_raw": 0.5628106427422491,
        "trend_quality_raw": 0.2411,
        "revenue_raw": 0.27126860702341604,
        "institutional_raw": 0.0,
        "industry": "電子工業"
      },
      {
        "symbol": "3653",
        "rank": 12,
        "portfolio_score": 67.95,
        "rank_components": {
          "price_momentum": 76.92,
          "trend_quality": 57.69,
          "revenue_momentum": 56.41
        },
        "price_momentum_raw": 0.6946357096567928,
        "trend_quality_raw": 0.221,
        "revenue_raw": 0.15499167332535793,
        "institutional_raw": 0.0,
        "industry": "電子零組件業"
      },
      {
        "symbol": "2383",
        "rank": 13,
        "portfolio_score": 67.47,
        "rank_components": {
          "price_momentum": 63.46,
          "trend_quality": 53.85,
          "revenue_momentum": 87.18
        },
        "price_momentum_raw": 0.5473811687875139,
        "trend_quality_raw": 0.1748,
        "revenue_raw": 0.497756823120474,
        "institutional_raw": 0.0,
        "industry": "電子零組件業"
      },
      {
        "symbol": "2449",
        "rank": 14,
        "portfolio_score": 65.9,
        "rank_components": {
          "price_momentum": 84.62,
          "trend_quality": 90.38,
          "revenue_momentum": 5.13
        },
        "price_momentum_raw": 0.8476374558779592,
        "trend_quality_raw": 0.5397,
        "revenue_raw": -0.19923426052051138,
        "institutional_raw": 0.0,
        "industry": "電子工業"
      },
      {
        "symbol": "2317",
        "rank": 15,
        "portfolio_score": 64.26,
        "rank_components": {
          "price_momentum": 78.85,
          "trend_quality": 30.77,
          "revenue_momentum": 58.97
        },
        "price_momentum_raw": 0.6986894740628823,
        "trend_quality_raw": 0.0267,
        "revenue_raw": 0.16460727620266122,
        "institutional_raw": 0.0,
        "industry": "電子工業"
      },
      {
        "symbol": "3533",
        "rank": 16,
        "portfolio_score": 63.37,
        "rank_components": {
          "price_momentum": 71.15,
          "trend_quality": 44.23,
          "revenue_momentum": 61.54
        },
        "price_momentum_raw": 0.5981942277164184,
        "trend_quality_raw": 0.1122,
        "revenue_raw": 0.18515983491453575,
        "institutional_raw": 0.0,
        "industry": "電子零組件業"
      },
      {
        "symbol": "3017",
        "rank": 17,
        "portfolio_score": 63.37,
        "rank_components": {
          "price_momentum": 86.54,
          "trend_quality": 11.54,
          "revenue_momentum": 53.85
        },
        "price_momentum_raw": 1.0330683344025056,
        "trend_quality_raw": 0.0,
        "revenue_raw": 0.1535576113422983,
        "institutional_raw": 0.0,
        "industry": "電子工業"
      },
      {
        "symbol": "2367",
        "rank": 18,
        "portfolio_score": 62.76,
        "rank_components": {
          "price_momentum": 80.77,
          "trend_quality": 11.54,
          "revenue_momentum": 64.1
        },
        "price_momentum_raw": 0.8071339005273426,
        "trend_quality_raw": 0.0,
        "revenue_raw": 0.20640295468285846,
        "institutional_raw": 0.0,
        "industry": "電子零組件業"
      },
      {
        "symbol": "8210",
        "rank": 19,
        "portfolio_score": 62.34,
        "rank_components": {
          "price_momentum": 55.77,
          "trend_quality": 46.15,
          "revenue_momentum": 89.74
        },
        "price_momentum_raw": 0.4292280544359788,
        "trend_quality_raw": 0.1218,
        "revenue_raw": 0.5116653227543305,
        "institutional_raw": 0.0,
        "industry": "電腦及週邊設備業"
      },
      {
        "symbol": "2382",
        "rank": 20,
        "portfolio_score": 60.45,
        "rank_components": {
          "price_momentum": 73.08,
          "trend_quality": 11.54,
          "revenue_momentum": 71.79
        },
        "price_momentum_raw": 0.6255042038287529,
        "trend_quality_raw": 0.0,
        "revenue_raw": 0.22320826909943386,
        "institutional_raw": 0.0,
        "industry": "電腦及週邊設備業"
      }
    ],
    "config_hash": "3bb0d8efab1de820",
    "score_dispersion": {
      "std": 20.4029,
      "iqr": 35.505,
      "n_eligible": 52
    }
  },
  {
    "rebalance_date": "2024-09-12T00:00:00",
    "market_signal": "risk_off",
    "gross_exposure": 0.3501,
    "total_analyzed": 80,
    "analysis_errors": 0,
    "eligible_candidates": 49,
    "selected_count": 8,
    "universe_size": 80,
    "universe_fingerprint": "dbec0ea9a223",
    "one_way_turnover": 0.1336,
    "trade_cost": 0.000762,
    "data_degraded": false,
    "data_degraded_reasons": [],
    "factor_coverage": {
      "revenue_momentum": 0.735,
      "institutional_flow": 0.0
    },
    "eligible_list": [
      "2467",
      "3450",
      "3167",
      "6515",
      "6805",
      "1560",
      "3653",
      "6442",
      "2489",
      "2367",
      "8039",
      "6139",
      "2330",
      "2357",
      "2360",
      "8210",
      "6451",
      "3533",
      "3665",
      "2449",
      "2317",
      "6919",
      "2454",
      "2383",
      "6257",
      "2345",
      "2059",
      "3017",
      "2327",
      "3189",
      "8021",
      "3563",
      "2313",
      "2308",
      "2891",
      "4906",
      "2426",
      "2303",
      "4958",
      "2382",
      "3711",
      "6830",
      "1717",
      "8996",
      "3714",
      "2337",
      "2481",
      "2355",
      "2027"
    ],
    "rejected_not_selected": [
      "3653",
      "2367",
      "8039",
      "6139",
      "2330",
      "2357",
      "2360",
      "8210",
      "6451",
      "3533",
      "3665",
      "2449",
      "2317",
      "6919",
      "2454",
      "2383",
      "6257",
      "2345",
      "2059",
      "3017",
      "2327",
      "3189",
      "8021",
      "3563",
      "2313",
      "2308",
      "2891",
      "4906",
      "2426",
      "2303",
      "4958",
      "2382",
      "3711",
      "6830",
      "1717",
      "8996",
      "3714",
      "2337",
      "2481",
      "2355",
      "2027"
    ],
    "rejected_by_top_n": [
      "2367",
      "8039",
      "6139",
      "2330",
      "2357",
      "2360",
      "8210",
      "6451",
      "3533",
      "3665",
      "2449",
      "2317",
      "6919",
      "2454",
      "2383",
      "6257",
      "2345",
      "2059",
      "3017",
      "2327",
      "3189",
      "8021",
      "3563",
      "2313",
      "2308",
      "2891",
      "4906",
      "2426",
      "2303",
      "4958",
      "2382",
      "3711",
      "6830",
      "1717",
      "8996",
      "3714",
      "2337",
      "2481",
      "2355",
      "2027"
    ],
    "rejected_by_turnover": [
      "2485",
      "1309",
      "1802",
      "8271"
    ],
    "rejected_by_price": [
      "2409",
      "3481",
      "2485",
      "1309",
      "1802"
    ],
    "rejected_by_history": [
      "7769",
      "7822"
    ],
    "rejected_by_trend": [
      "3037",
      "2344",
      "2408",
      "8046",
      "6285",
      "1303",
      "2368",
      "6770",
      "3715",
      "6213",
      "2455",
      "2485",
      "3661",
      "6669",
      "3006",
      "6239",
      "3231",
      "3443",
      "2486",
      "8271",
      "4967",
      "2404",
      "6531",
      "6781",
      "1326"
    ],
    "rejected_by_industry": [],
    "positions": [
      {
        "symbol": "2467",
        "weight": 0.0504,
        "score": 93.36,
        "industry": "電子零組件業"
      },
      {
        "symbol": "3450",
        "weight": 0.0503,
        "score": 93.18,
        "industry": "電子工業"
      },
      {
        "symbol": "3167",
        "weight": 0.0494,
        "score": 91.63,
        "industry": "電機機械"
      },
      {
        "symbol": "6515",
        "weight": 0.0423,
        "score": 78.52,
        "industry": "半導體業"
      },
      {
        "symbol": "6805",
        "weight": 0.0421,
        "score": 78.01,
        "industry": "電子零組件業"
      },
      {
        "symbol": "1560",
        "weight": 0.04,
        "score": 74.13,
        "industry": "電機機械"
      },
      {
        "symbol": "6442",
        "weight": 0.0386,
        "score": 71.58,
        "industry": "通信網路業"
      },
      {
        "symbol": "2489",
        "weight": 0.037,
        "score": 68.53,
        "industry": "電子工業"
      }
    ],
    "theme_concentration": {
      "tech_weight": 0.3501,
      "tech_count": 8,
      "total_positions": 8,
      "top_industry": "電子零組件業",
      "top_industry_weight": 0.0925,
      "industries": {
        "電子零組件業": 0.0925,
        "電機機械": 0.0894,
        "電子工業": 0.0873,
        "半導體業": 0.0423,
        "通信網路業": 0.0386
      }
    },
    "factor_detail": [
      {
        "symbol": "2467",
        "rank": 1,
        "portfolio_score": 93.36,
        "rank_components": {
          "price_momentum": 97.96,
          "trend_quality": 89.8,
          "revenue_momentum": 86.11
        },
        "price_momentum_raw": 1.6378594084754157,
        "trend_quality_raw": 0.5731,
        "revenue_raw": 0.3806948287633028,
        "institutional_raw": 0.0,
        "industry": "電子零組件業"
      },
      {
        "symbol": "3450",
        "rank": 2,
        "portfolio_score": 93.18,
        "rank_components": {
          "price_momentum": 95.92,
          "trend_quality": 97.96,
          "revenue_momentum": 83.33
        },
        "price_momentum_raw": 1.481267469522094,
        "trend_quality_raw": 0.85,
        "revenue_raw": 0.37231227653580107,
        "institutional_raw": 0.0,
        "industry": "電子工業"
      },
      {
        "symbol": "3167",
        "rank": 3,
        "portfolio_score": 91.63,
        "rank_components": {
          "price_momentum": 87.76,
          "trend_quality": 91.84,
          "revenue_momentum": 100.0
        },
        "price_momentum_raw": 0.71872123436357,
        "trend_quality_raw": 0.5754,
        "revenue_raw": 1.2899746910309762,
        "institutional_raw": 0.0,
        "industry": "電機機械"
      },
      {
        "symbol": "6515",
        "rank": 4,
        "portfolio_score": 78.52,
        "rank_components": {
          "price_momentum": 83.67,
          "trend_quality": 100.0,
          "revenue_momentum": 50.0
        },
        "price_momentum_raw": 0.5473539778449144,
        "trend_quality_raw": 0.966,
        "revenue_raw": null,
        "institutional_raw": 0.0,
        "industry": "半導體業"
      },
      {
        "symbol": "6805",
        "rank": 5,
        "portfolio_score": 78.01,
        "rank_components": {
          "price_momentum": 93.88,
          "trend_quality": 69.39,
          "revenue_momentum": 50.0
        },
        "price_momentum_raw": 1.2916166602576895,
        "trend_quality_raw": 0.2627,
        "revenue_raw": null,
        "institutional_raw": 0.0,
        "industry": "電子零組件業"
      },
      {
        "symbol": "1560",
        "rank": 6,
        "portfolio_score": 74.13,
        "rank_components": {
          "price_momentum": 89.8,
          "trend_quality": 61.22,
          "revenue_momentum": 50.0
        },
        "price_momentum_raw": 0.7357727748206805,
        "trend_quality_raw": 0.2,
        "revenue_raw": 0.1931038526756083,
        "institutional_raw": 0.0,
        "industry": "電機機械"
      },
      {
        "symbol": "3653",
        "rank": 7,
        "portfolio_score": 72.62,
        "rank_components": {
          "price_momentum": 85.71,
          "trend_quality": 85.71,
          "revenue_momentum": 33.33
        },
        "price_momentum_raw": 0.6905801563048055,
        "trend_quality_raw": 0.5077,
        "revenue_raw": 0.12004693084540889,
        "institutional_raw": 0.0,
        "industry": "電子零組件業"
      },
      {
        "symbol": "6442",
        "rank": 8,
        "portfolio_score": 71.58,
        "rank_components": {
          "price_momentum": 100.0,
          "trend_quality": 20.41,
          "revenue_momentum": 50.0
        },
        "price_momentum_raw": 2.519707553871655,
        "trend_quality_raw": 0.0255,
        "revenue_raw": null,
        "institutional_raw": 0.0,
        "industry": "通信網路業"
      },
      {
        "symbol": "2489",
        "rank": 9,
        "portfolio_score": 68.53,
        "rank_components": {
          "price_momentum": 67.35,
          "trend_quality": 42.86,
          "revenue_momentum": 91.67
        },
        "price_momentum_raw": 0.4109325151022919,
        "trend_quality_raw": 0.1302,
        "revenue_raw": 0.6107892897054408,
        "institutional_raw": 0.0,
        "industry": "電子工業"
      },
      {
        "symbol": "2367",
        "rank": 10,
        "portfolio_score": 66.71,
        "rank_components": {
          "price_momentum": 81.63,
          "trend_quality": 32.65,
          "revenue_momentum": 61.11
        },
        "price_momentum_raw": 0.5365109321542032,
        "trend_quality_raw": 0.0658,
        "revenue_raw": 0.22337707400727552,
        "institutional_raw": 0.0,
        "industry": "電子零組件業"
      },
      {
        "symbol": "8039",
        "rank": 11,
        "portfolio_score": 66.48,
        "rank_components": {
          "price_momentum": 63.27,
          "trend_quality": 95.92,
          "revenue_momentum": 50.0
        },
        "price_momentum_raw": 0.29195253966486817,
        "trend_quality_raw": 0.746,
        "revenue_raw": null,
        "institutional_raw": 0.0,
        "industry": "電子零組件業"
      },
      {
        "symbol": "6139",
        "rank": 12,
        "portfolio_score": 65.87,
        "rank_components": {
          "price_momentum": 91.84,
          "trend_quality": 14.29,
          "revenue_momentum": 50.0
        },
        "price_momentum_raw": 0.9514395819517139,
        "trend_quality_raw": 0.0164,
        "revenue_raw": null,
        "institutional_raw": 0.0,
        "industry": "其他電子業"
      },
      {
        "symbol": "2330",
        "rank": 13,
        "portfolio_score": 64.34,
        "rank_components": {
          "price_momentum": 65.31,
          "trend_quality": 44.9,
          "revenue_momentum": 77.78
        },
        "price_momentum_raw": 0.3842238646373575,
        "trend_quality_raw": 0.1315,
        "revenue_raw": 0.3525968676576632,
        "institutional_raw": 0.0,
        "industry": "電子工業"
      },
      {
        "symbol": "2357",
        "rank": 14,
        "portfolio_score": 64.01,
        "rank_components": {
          "price_momentum": 57.14,
          "trend_quality": 79.59,
          "revenue_momentum": 66.67
        },
        "price_momentum_raw": 0.26606849778837594,
        "trend_quality_raw": 0.4317,
        "revenue_raw": 0.238576885857135,
        "institutional_raw": 0.0,
        "industry": "電腦及週邊設備業"
      },
      {
        "symbol": "2360",
        "rank": 15,
        "portfolio_score": 63.34,
        "rank_components": {
          "price_momentum": 46.94,
          "trend_quality": 93.88,
          "revenue_momentum": 75.0
        },
        "price_momentum_raw": 0.21253127985486428,
        "trend_quality_raw": 0.6983,
        "revenue_raw": 0.32218485385699736,
        "institutional_raw": 0.0,
        "industry": "其他電子業"
      },
      {
        "symbol": "8210",
        "rank": 16,
        "portfolio_score": 63.29,
        "rank_components": {
          "price_momentum": 53.06,
          "trend_quality": 48.98,
          "revenue_momentum": 97.22
        },
        "price_momentum_raw": 0.2301594258349896,
        "trend_quality_raw": 0.1496,
        "revenue_raw": 0.9316513909660448,
        "institutional_raw": 0.0,
        "industry": "電腦及週邊設備業"
      },
      {
        "symbol": "6451",
        "rank": 17,
        "portfolio_score": 62.5,
        "rank_components": {
          "price_momentum": 77.55,
          "trend_quality": 36.73,
          "revenue_momentum": 50.0
        },
        "price_momentum_raw": 0.49621601398406,
        "trend_quality_raw": 0.0775,
        "revenue_raw": null,
        "institutional_raw": 0.0,
        "industry": "半導體業"
      },
      {
        "symbol": "3533",
        "rank": 18,
        "portfolio_score": 61.54,
        "rank_components": {
          "price_momentum": 75.51,
          "trend_quality": 30.61,
          "revenue_momentum": 55.56
        },
        "price_momentum_raw": 0.48526785714285714,
        "trend_quality_raw": 0.0573,
        "revenue_raw": 0.22281180137554119,
        "institutional_raw": 0.0,
        "industry": "電子零組件業"
      },
      {
        "symbol": "3665",
        "rank": 19,
        "portfolio_score": 61.43,
        "rank_components": {
          "price_momentum": 69.39,
          "trend_quality": 81.63,
          "revenue_momentum": 27.78
        },
        "price_momentum_raw": 0.45841506565493484,
        "trend_quality_raw": 0.4531,
        "revenue_raw": 0.11030830557909427,
        "institutional_raw": 0.0,
        "industry": "電子工業"
      },
      {
        "symbol": "2449",
        "rank": 20,
        "portfolio_score": 57.82,
        "rank_components": {
          "price_momentum": 79.59,
          "trend_quality": 63.27,
          "revenue_momentum": 5.56
        },
        "price_momentum_raw": 0.4993477543356577,
        "trend_quality_raw": 0.2351,
        "revenue_raw": -0.152423084776037,
        "institutional_raw": 0.0,
        "industry": "電子工業"
      }
    ],
    "config_hash": "3bb0d8efab1de820",
    "score_dispersion": {
      "std": 20.2232,
      "iqr": 25.84,
      "n_eligible": 49
    }
  },
  {
    "rebalance_date": "2024-10-14T00:00:00",
    "market_signal": "caution",
    "gross_exposure": 0.7,
    "total_analyzed": 80,
    "analysis_errors": 0,
    "eligible_candidates": 20,
    "selected_count": 6,
    "universe_size": 80,
    "universe_fingerprint": "dbec0ea9a223",
    "one_way_turnover": 0.3328,
    "trade_cost": 0.001897,
    "data_degraded": false,
    "data_degraded_reasons": [],
    "factor_coverage": {
      "revenue_momentum": 0.7,
      "institutional_flow": 0.0
    },
    "eligible_list": [
      "3450",
      "3167",
      "6805",
      "2330",
      "3653",
      "2467",
      "1560",
      "6515",
      "2426",
      "2317",
      "2360",
      "3533",
      "3665",
      "2357",
      "6830",
      "2345",
      "6257",
      "1717",
      "3714",
      "3711"
    ],
    "rejected_not_selected": [
      "1560",
      "6515",
      "2426",
      "2317",
      "2360",
      "3533",
      "3665",
      "2357",
      "6830",
      "2345",
      "6257",
      "1717",
      "3714",
      "3711"
    ],
    "rejected_by_top_n": [
      "2426",
      "2317",
      "2360",
      "3533",
      "3665",
      "2357",
      "6830",
      "2345",
      "6257",
      "1717",
      "3714",
      "3711"
    ],
    "rejected_by_turnover": [
      "2485",
      "8271"
    ],
    "rejected_by_price": [
      "2409",
      "3481",
      "2485",
      "1309",
      "1802"
    ],
    "rejected_by_history": [
      "7769",
      "7822"
    ],
    "rejected_by_trend": [
      "2313",
      "3037",
      "2344",
      "2308",
      "2408",
      "8046",
      "2454",
      "2303",
      "2383",
      "3017",
      "4958",
      "6285",
      "2367",
      "1303",
      "6442",
      "2409",
      "2368",
      "6770",
      "3715",
      "6213",
      "8039",
      "2481",
      "2455",
      "2485",
      "3661",
      "2449",
      "8021",
      "3189",
      "6669",
      "8996",
      "2327",
      "3006",
      "2891",
      "4906",
      "6451",
      "8210",
      "2382",
      "6239",
      "3231",
      "3443",
      "2489",
      "2337",
      "1802",
      "3563",
      "2355",
      "2486",
      "8271",
      "6919",
      "4967",
      "2404",
      "2059",
      "6531",
      "6139",
      "6781",
      "1326",
      "2027"
    ],
    "rejected_by_industry": [],
    "positions": [
      {
        "symbol": "3450",
        "weight": 0.12,
        "score": 97.71,
        "industry": "電子工業"
      },
      {
        "symbol": "3167",
        "weight": 0.12,
        "score": 91.25,
        "industry": "電機機械"
      },
      {
        "symbol": "6805",
        "weight": 0.12,
        "score": 76.0,
        "industry": "電子零組件業"
      },
      {
        "symbol": "2330",
        "weight": 0.116,
        "score": 66.43,
        "industry": "電子工業"
      },
      {
        "symbol": "3653",
        "weight": 0.1132,
        "score": 64.61,
        "industry": "電子零組件業"
      },
      {
        "symbol": "2467",
        "weight": 0.1108,
        "score": 63.04,
        "industry": "電子零組件業"
      }
    ],
    "theme_concentration": {
      "tech_weight": 0.7,
      "tech_count": 6,
      "total_positions": 6,
      "top_industry": "電子零組件業",
      "top_industry_weight": 0.344,
      "industries": {
        "電子零組件業": 0.344,
        "電子工業": 0.236,
        "電機機械": 0.12
      }
    },
    "factor_detail": [
      {
        "symbol": "3450",
        "rank": 1,
        "portfolio_score": 97.71,
        "rank_components": {
          "price_momentum": 100.0,
          "trend_quality": 97.5,
          "revenue_momentum": 92.86
        },
        "price_momentum_raw": 2.3245473704377813,
        "trend_quality_raw": 1.0,
        "revenue_raw": 0.31783479670820275,
        "institutional_raw": 0.0,
        "industry": "電子工業"
      },
      {
        "symbol": "3167",
        "rank": 2,
        "portfolio_score": 91.25,
        "rank_components": {
          "price_momentum": 85.0,
          "trend_quality": 97.5,
          "revenue_momentum": 100.0
        },
        "price_momentum_raw": 1.2914182763115059,
        "trend_quality_raw": 1.0,
        "revenue_raw": 0.8975431841793564,
        "institutional_raw": 0.0,
        "industry": "電機機械"
      },
      {
        "symbol": "6805",
        "rank": 3,
        "portfolio_score": 76.0,
        "rank_components": {
          "price_momentum": 90.0,
          "trend_quality": 70.0,
          "revenue_momentum": 50.0
        },
        "price_momentum_raw": 1.3203523793309877,
        "trend_quality_raw": 0.766,
        "revenue_raw": null,
        "institutional_raw": 0.0,
        "industry": "電子零組件業"
      },
      {
        "symbol": "2330",
        "rank": 4,
        "portfolio_score": 66.43,
        "rank_components": {
          "price_momentum": 60.0,
          "trend_quality": 60.0,
          "revenue_momentum": 85.71
        },
        "price_momentum_raw": 0.38442798094437436,
        "trend_quality_raw": 0.6553,
        "revenue_raw": 0.25557287616792157,
        "institutional_raw": 0.0,
        "industry": "電子工業"
      },
      {
        "symbol": "3653",
        "rank": 5,
        "portfolio_score": 64.61,
        "rank_components": {
          "price_momentum": 75.0,
          "trend_quality": 90.0,
          "revenue_momentum": 21.43
        },
        "price_momentum_raw": 0.6847322685054883,
        "trend_quality_raw": 0.9351,
        "revenue_raw": 0.03811387926914624,
        "institutional_raw": 0.0,
        "industry": "電子零組件業"
      },
      {
        "symbol": "2467",
        "rank": 6,
        "portfolio_score": 63.04,
        "rank_components": {
          "price_momentum": 95.0,
          "trend_quality": 45.0,
          "revenue_momentum": 7.14
        },
        "price_momentum_raw": 2.02569606789058,
        "trend_quality_raw": 0.5661,
        "revenue_raw": -0.015807691377362997,
        "institutional_raw": 0.0,
        "industry": "電子零組件業"
      },
      {
        "symbol": "1560",
        "rank": 7,
        "portfolio_score": 59.93,
        "rank_components": {
          "price_momentum": 80.0,
          "trend_quality": 35.0,
          "revenue_momentum": 35.71
        },
        "price_momentum_raw": 0.7025511900405519,
        "trend_quality_raw": 0.5087,
        "revenue_raw": 0.0537875225785525,
        "institutional_raw": 0.0,
        "industry": "電機機械"
      },
      {
        "symbol": "6515",
        "rank": 8,
        "portfolio_score": 59.0,
        "rank_components": {
          "price_momentum": 70.0,
          "trend_quality": 40.0,
          "revenue_momentum": 50.0
        },
        "price_momentum_raw": 0.6716055032469667,
        "trend_quality_raw": 0.5368,
        "revenue_raw": null,
        "institutional_raw": 0.0,
        "industry": "半導體業"
      },
      {
        "symbol": "2426",
        "rank": 9,
        "portfolio_score": 58.75,
        "rank_components": {
          "price_momentum": 55.0,
          "trend_quality": 80.0,
          "revenue_momentum": 50.0
        },
        "price_momentum_raw": 0.3486887398261778,
        "trend_quality_raw": 0.8368,
        "revenue_raw": 0.1317561280216081,
        "institutional_raw": 0.0,
        "industry": "電子工業"
      },
      {
        "symbol": "2317",
        "rank": 10,
        "portfolio_score": 57.14,
        "rank_components": {
          "price_momentum": 50.0,
          "trend_quality": 50.0,
          "revenue_momentum": 78.57
        },
        "price_momentum_raw": 0.3339861255344429,
        "trend_quality_raw": 0.5777,
        "revenue_raw": 0.25014678488489733,
        "institutional_raw": 0.0,
        "industry": "電子工業"
      },
      {
        "symbol": "2360",
        "rank": 11,
        "portfolio_score": 50.46,
        "rank_components": {
          "price_momentum": 45.0,
          "trend_quality": 75.0,
          "revenue_momentum": 42.86
        },
        "price_momentum_raw": 0.33090837990984573,
        "trend_quality_raw": 0.8236,
        "revenue_raw": 0.07675038712570764,
        "institutional_raw": 0.0,
        "industry": "其他電子業"
      },
      {
        "symbol": "3533",
        "rank": 12,
        "portfolio_score": 49.29,
        "rank_components": {
          "price_momentum": 40.0,
          "trend_quality": 65.0,
          "revenue_momentum": 57.14
        },
        "price_momentum_raw": 0.31604237320428313,
        "trend_quality_raw": 0.6657,
        "revenue_raw": 0.1703438520796166,
        "institutional_raw": 0.0,
        "industry": "電子零組件業"
      },
      {
        "symbol": "3665",
        "rank": 13,
        "portfolio_score": 48.89,
        "rank_components": {
          "price_momentum": 65.0,
          "trend_quality": 30.0,
          "revenue_momentum": 28.57
        },
        "price_momentum_raw": 0.6446032607026623,
        "trend_quality_raw": 0.497,
        "revenue_raw": 0.05027281842590582,
        "institutional_raw": 0.0,
        "industry": "電子工業"
      },
      {
        "symbol": "2357",
        "rank": 14,
        "portfolio_score": 46.32,
        "rank_components": {
          "price_momentum": 35.0,
          "trend_quality": 55.0,
          "revenue_momentum": 64.29
        },
        "price_momentum_raw": 0.3120109895277055,
        "trend_quality_raw": 0.6012,
        "revenue_raw": 0.18154938201637155,
        "institutional_raw": 0.0,
        "industry": "電腦及週邊設備業"
      },
      {
        "symbol": "6830",
        "rank": 15,
        "portfolio_score": 46.0,
        "rank_components": {
          "price_momentum": 30.0,
          "trend_quality": 85.0,
          "revenue_momentum": 50.0
        },
        "price_momentum_raw": 0.23909111012826184,
        "trend_quality_raw": 0.85,
        "revenue_raw": null,
        "institutional_raw": 0.0,
        "industry": "其他電子業"
      },
      {
        "symbol": "2345",
        "rank": 16,
        "portfolio_score": 31.86,
        "rank_components": {
          "price_momentum": 20.0,
          "trend_quality": 15.0,
          "revenue_momentum": 71.43
        },
        "price_momentum_raw": 0.09742705310917682,
        "trend_quality_raw": 0.4101,
        "revenue_raw": 0.23359771765613044,
        "institutional_raw": 0.0,
        "industry": "電子工業"
      },
      {
        "symbol": "6257",
        "rank": 17,
        "portfolio_score": 28.25,
        "rank_components": {
          "price_momentum": 25.0,
          "trend_quality": 10.0,
          "revenue_momentum": 50.0
        },
        "price_momentum_raw": 0.1840719143703353,
        "trend_quality_raw": 0.3442,
        "revenue_raw": null,
        "institutional_raw": 0.0,
        "industry": "電子工業"
      },
      {
        "symbol": "1717",
        "rank": 18,
        "portfolio_score": 23.0,
        "rank_components": {
          "price_momentum": 10.0,
          "trend_quality": 25.0,
          "revenue_momentum": 50.0
        },
        "price_momentum_raw": 0.022260613737834466,
        "trend_quality_raw": 0.4612,
        "revenue_raw": null,
        "institutional_raw": 0.0,
        "industry": "化學生技醫療"
      },
      {
        "symbol": "3714",
        "rank": 19,
        "portfolio_score": 19.25,
        "rank_components": {
          "price_momentum": 5.0,
          "trend_quality": 20.0,
          "revenue_momentum": 50.0
        },
        "price_momentum_raw": 0.018233259339477757,
        "trend_quality_raw": 0.4426,
        "revenue_raw": null,
        "institutional_raw": 0.0,
        "industry": "光電業"
      },
      {
        "symbol": "3711",
        "rank": 20,
        "portfolio_score": 12.82,
        "rank_components": {
          "price_momentum": 15.0,
          "trend_quality": 5.0,
          "revenue_momentum": 14.29
        },
        "price_momentum_raw": 0.0670175249587014,
        "trend_quality_raw": 0.2769,
        "revenue_raw": 0.03565006494979728,
        "institutional_raw": 0.0,
        "industry": "電子工業"
      }
    ],
    "config_hash": "3bb0d8efab1de820",
    "score_dispersion": {
      "std": 21.6563,
      "iqr": 20.9675,
      "n_eligible": 20
    }
  },
  {
    "rebalance_date": "2024-11-12T00:00:00",
    "market_signal": "caution",
    "gross_exposure": 0.7,
    "total_analyzed": 80,
    "analysis_errors": 0,
    "eligible_candidates": 26,
    "selected_count": 8,
    "universe_size": 80,
    "universe_fingerprint": "dbec0ea9a223",
    "one_way_turnover": 0.2577,
    "trade_cost": 0.001469,
    "data_degraded": false,
    "data_degraded_reasons": [],
    "factor_coverage": {
      "revenue_momentum": 0.731,
      "institutional_flow": 0.0
    },
    "eligible_list": [
      "3450",
      "3167",
      "6442",
      "3653",
      "3665",
      "6515",
      "3533",
      "2330",
      "6805",
      "2382",
      "2486",
      "2357",
      "2360",
      "2059",
      "2317",
      "6451",
      "2891",
      "8210",
      "2449",
      "6830",
      "2454",
      "2345",
      "6781",
      "3231",
      "3714",
      "2308"
    ],
    "rejected_not_selected": [
      "3533",
      "2382",
      "2486",
      "2357",
      "2360",
      "2059",
      "2317",
      "6451",
      "2891",
      "8210",
      "2449",
      "6830",
      "2454",
      "2345",
      "6781",
      "3231",
      "3714",
      "2308"
    ],
    "rejected_by_top_n": [
      "2382",
      "2486",
      "2357",
      "2360",
      "2059",
      "2317",
      "6451",
      "2891",
      "8210",
      "2449",
      "6830",
      "2454",
      "2345",
      "6781",
      "3231",
      "3714",
      "2308"
    ],
    "rejected_by_turnover": [
      "2485",
      "1309",
      "2355",
      "8271"
    ],
    "rejected_by_price": [
      "2344",
      "2409",
      "6770",
      "3481",
      "2485",
      "1309",
      "1802"
    ],
    "rejected_by_history": [
      "7769",
      "7822"
    ],
    "rejected_by_trend": [
      "2313",
      "3037",
      "2344",
      "2408",
      "8046",
      "2303",
      "2383",
      "3017",
      "4958",
      "6285",
      "2367",
      "1303",
      "2409",
      "2368",
      "6770",
      "3715",
      "6213",
      "3711",
      "8039",
      "2481",
      "2455",
      "3481",
      "2485",
      "3661",
      "8021",
      "3189",
      "6669",
      "8996",
      "2327",
      "6257",
      "3006",
      "4906",
      "6239",
      "3443",
      "1309",
      "2489",
      "2337",
      "2426",
      "3563",
      "2355",
      "8271",
      "6919",
      "2467",
      "4967",
      "2404",
      "1560",
      "1717",
      "6531",
      "6139",
      "1326",
      "2027"
    ],
    "rejected_by_industry": [],
    "positions": [
      {
        "symbol": "3450",
        "weight": 0.1096,
        "score": 94.48,
        "industry": "電子工業"
      },
      {
        "symbol": "3167",
        "weight": 0.1057,
        "score": 91.15,
        "industry": "電機機械"
      },
      {
        "symbol": "6442",
        "weight": 0.1015,
        "score": 87.5,
        "industry": "通信網路業"
      },
      {
        "symbol": "3653",
        "weight": 0.0805,
        "score": 69.4,
        "industry": "電子零組件業"
      },
      {
        "symbol": "3665",
        "weight": 0.079,
        "score": 68.15,
        "industry": "電子工業"
      },
      {
        "symbol": "6515",
        "weight": 0.0772,
        "score": 66.54,
        "industry": "半導體業"
      },
      {
        "symbol": "2330",
        "weight": 0.0736,
        "score": 63.42,
        "industry": "電子工業"
      },
      {
        "symbol": "6805",
        "weight": 0.0729,
        "score": 62.88,
        "industry": "電子零組件業"
      }
    ],
    "theme_concentration": {
      "tech_weight": 0.7,
      "tech_count": 8,
      "total_positions": 8,
      "top_industry": "電子工業",
      "top_industry_weight": 0.2622,
      "industries": {
        "電子工業": 0.2622,
        "電子零組件業": 0.1534,
        "電機機械": 0.1057,
        "通信網路業": 0.1015,
        "半導體業": 0.0772
      }
    },
    "factor_detail": [
      {
        "symbol": "3450",
        "rank": 1,
        "portfolio_score": 94.48,
        "rank_components": {
          "price_momentum": 96.15,
          "trend_quality": 96.15,
          "revenue_momentum": 89.47
        },
        "price_momentum_raw": 2.322893533184077,
        "trend_quality_raw": 0.9619,
        "revenue_raw": 0.5114919803917116,
        "institutional_raw": 0.0,
        "industry": "電子工業"
      },
      {
        "symbol": "3167",
        "rank": 2,
        "portfolio_score": 91.15,
        "rank_components": {
          "price_momentum": 92.31,
          "trend_quality": 76.92,
          "revenue_momentum": 100.0
        },
        "price_momentum_raw": 1.585786648778727,
        "trend_quality_raw": 0.8286,
        "revenue_raw": 1.043425933306239,
        "institutional_raw": 0.0,
        "industry": "電機機械"
      },
      {
        "symbol": "6442",
        "rank": 3,
        "portfolio_score": 87.5,
        "rank_components": {
          "price_momentum": 100.0,
          "trend_quality": 100.0,
          "revenue_momentum": 50.0
        },
        "price_momentum_raw": 2.998886491831825,
        "trend_quality_raw": 0.9838,
        "revenue_raw": null,
        "institutional_raw": 0.0,
        "industry": "通信網路業"
      },
      {
        "symbol": "3653",
        "rank": 4,
        "portfolio_score": 69.4,
        "rank_components": {
          "price_momentum": 88.46,
          "trend_quality": 57.69,
          "revenue_momentum": 36.84
        },
        "price_momentum_raw": 0.9827978977908989,
        "trend_quality_raw": 0.7056,
        "revenue_raw": 0.13644707842501672,
        "institutional_raw": 0.0,
        "industry": "電子零組件業"
      },
      {
        "symbol": "3665",
        "rank": 5,
        "portfolio_score": 68.15,
        "rank_components": {
          "price_momentum": 80.77,
          "trend_quality": 92.31,
          "revenue_momentum": 21.05
        },
        "price_momentum_raw": 0.9327841951951777,
        "trend_quality_raw": 0.961,
        "revenue_raw": 0.07074589774260279,
        "institutional_raw": 0.0,
        "industry": "電子工業"
      },
      {
        "symbol": "6515",
        "rank": 6,
        "portfolio_score": 66.54,
        "rank_components": {
          "price_momentum": 73.08,
          "trend_quality": 69.23,
          "revenue_momentum": 50.0
        },
        "price_momentum_raw": 0.663328437132785,
        "trend_quality_raw": 0.7754,
        "revenue_raw": null,
        "institutional_raw": 0.0,
        "industry": "半導體業"
      },
      {
        "symbol": "3533",
        "rank": 7,
        "portfolio_score": 63.96,
        "rank_components": {
          "price_momentum": 65.38,
          "trend_quality": 80.77,
          "revenue_momentum": 47.37
        },
        "price_momentum_raw": 0.5591524556231833,
        "trend_quality_raw": 0.8655,
        "revenue_raw": 0.2053070389621004,
        "institutional_raw": 0.0,
        "industry": "電子零組件業"
      },
      {
        "symbol": "2330",
        "rank": 8,
        "portfolio_score": 63.42,
        "rank_components": {
          "price_momentum": 69.23,
          "trend_quality": 34.62,
          "revenue_momentum": 73.68
        },
        "price_momentum_raw": 0.588318712148201,
        "trend_quality_raw": 0.6036,
        "revenue_raw": 0.3155569546770228,
        "institutional_raw": 0.0,
        "industry": "電子工業"
      },
      {
        "symbol": "6805",
        "rank": 9,
        "portfolio_score": 62.88,
        "rank_components": {
          "price_momentum": 84.62,
          "trend_quality": 19.23,
          "revenue_momentum": 50.0
        },
        "price_momentum_raw": 0.9614145054750061,
        "trend_quality_raw": 0.419,
        "revenue_raw": null,
        "institutional_raw": 0.0,
        "industry": "電子零組件業"
      },
      {
        "symbol": "2382",
        "rank": 10,
        "portfolio_score": 55.8,
        "rank_components": {
          "price_momentum": 34.62,
          "trend_quality": 65.38,
          "revenue_momentum": 94.74
        },
        "price_momentum_raw": 0.2228862041815642,
        "trend_quality_raw": 0.7714,
        "revenue_raw": 0.5159290227481027,
        "institutional_raw": 0.0,
        "industry": "電腦及週邊設備業"
      },
      {
        "symbol": "2486",
        "rank": 11,
        "portfolio_score": 55.04,
        "rank_components": {
          "price_momentum": 76.92,
          "trend_quality": 30.77,
          "revenue_momentum": 26.32
        },
        "price_momentum_raw": 0.9166100291751397,
        "trend_quality_raw": 0.5783,
        "revenue_raw": 0.0988786160105515,
        "institutional_raw": 0.0,
        "industry": "電子工業"
      },
      {
        "symbol": "2357",
        "rank": 12,
        "portfolio_score": 52.74,
        "rank_components": {
          "price_momentum": 50.0,
          "trend_quality": 53.85,
          "revenue_momentum": 57.89
        },
        "price_momentum_raw": 0.44326731126645885,
        "trend_quality_raw": 0.6585,
        "revenue_raw": 0.2337870262289169,
        "institutional_raw": 0.0,
        "industry": "電腦及週邊設備業"
      },
      {
        "symbol": "2360",
        "rank": 13,
        "portfolio_score": 51.29,
        "rank_components": {
          "price_momentum": 57.69,
          "trend_quality": 84.62,
          "revenue_momentum": 10.53
        },
        "price_momentum_raw": 0.5525449105273257,
        "trend_quality_raw": 0.9436,
        "revenue_raw": 0.053571379089644953,
        "institutional_raw": 0.0,
        "industry": "其他電子業"
      },
      {
        "symbol": "2059",
        "rank": 14,
        "portfolio_score": 51.28,
        "rank_components": {
          "price_momentum": 30.77,
          "trend_quality": 73.08,
          "revenue_momentum": 78.95
        },
        "price_momentum_raw": 0.21923424781429002,
        "trend_quality_raw": 0.808,
        "revenue_raw": 0.44244179466478095,
        "institutional_raw": 0.0,
        "industry": "電子零組件業"
      },
      {
        "symbol": "2317",
        "rank": 15,
        "portfolio_score": 50.2,
        "rank_components": {
          "price_momentum": 61.54,
          "trend_quality": 42.31,
          "revenue_momentum": 31.58
        },
        "price_momentum_raw": 0.5567421746309094,
        "trend_quality_raw": 0.612,
        "revenue_raw": 0.13494543968648742,
        "institutional_raw": 0.0,
        "industry": "電子工業"
      },
      {
        "symbol": "6451",
        "rank": 16,
        "portfolio_score": 40.96,
        "rank_components": {
          "price_momentum": 46.15,
          "trend_quality": 15.38,
          "revenue_momentum": 50.0
        },
        "price_momentum_raw": 0.43329634483228174,
        "trend_quality_raw": 0.4053,
        "revenue_raw": null,
        "institutional_raw": 0.0,
        "industry": "半導體業"
      },
      {
        "symbol": "2891",
        "rank": 17,
        "portfolio_score": 39.83,
        "rank_components": {
          "price_momentum": 26.92,
          "trend_quality": 46.15,
          "revenue_momentum": 63.16
        },
        "price_momentum_raw": 0.21801629490653873,
        "trend_quality_raw": 0.6132,
        "revenue_raw": 0.2415342562585937,
        "institutional_raw": 0.0,
        "industry": "金融保險"
      },
      {
        "symbol": "8210",
        "rank": 18,
        "portfolio_score": 39.51,
        "rank_components": {
          "price_momentum": 15.38,
          "trend_quality": 50.0,
          "revenue_momentum": 84.21
        },
        "price_momentum_raw": 0.13969519704433506,
        "trend_quality_raw": 0.6188,
        "revenue_raw": 0.4879987978000404,
        "institutional_raw": 0.0,
        "industry": "電腦及週邊設備業"
      },
      {
        "symbol": "2449",
        "rank": 19,
        "portfolio_score": 38.62,
        "rank_components": {
          "price_momentum": 53.85,
          "trend_quality": 38.46,
          "revenue_momentum": 5.26
        },
        "price_momentum_raw": 0.498384740719364,
        "trend_quality_raw": 0.6051,
        "revenue_raw": -0.10358596929898199,
        "institutional_raw": 0.0,
        "industry": "電子工業"
      },
      {
        "symbol": "6830",
        "rank": 20,
        "portfolio_score": 38.27,
        "rank_components": {
          "price_momentum": 38.46,
          "trend_quality": 23.08,
          "revenue_momentum": 50.0
        },
        "price_momentum_raw": 0.4039089851387359,
        "trend_quality_raw": 0.4804,
        "revenue_raw": null,
        "institutional_raw": 0.0,
        "industry": "其他電子業"
      }
    ],
    "config_hash": "3bb0d8efab1de820",
    "score_dispersion": {
      "std": 20.0403,
      "iqr": 25.4675,
      "n_eligible": 26
    }
  },
  {
    "rebalance_date": "2024-12-12T00:00:00",
    "market_signal": "caution",
    "gross_exposure": 0.7,
    "total_analyzed": 80,
    "analysis_errors": 0,
    "eligible_candidates": 24,
    "selected_count": 7,
    "universe_size": 80,
    "universe_fingerprint": "dbec0ea9a223",
    "one_way_turnover": 0.2565,
    "trade_cost": 0.001462,
    "data_degraded": false,
    "data_degraded_reasons": [],
    "factor_coverage": {
      "revenue_momentum": 0.75,
      "institutional_flow": 0.0
    },
    "eligible_list": [
      "3450",
      "6442",
      "6805",
      "2059",
      "3563",
      "3665",
      "3533",
      "3017",
      "3653",
      "2486",
      "2345",
      "6781",
      "2330",
      "6451",
      "2891",
      "2383",
      "2404",
      "2357",
      "2454",
      "2308",
      "6919",
      "3231",
      "4958",
      "2455"
    ],
    "rejected_not_selected": [
      "3533",
      "3017",
      "2486",
      "2345",
      "6781",
      "2330",
      "6451",
      "2891",
      "2383",
      "2404",
      "2357",
      "2454",
      "2308",
      "6919",
      "3231",
      "4958",
      "2455"
    ],
    "rejected_by_top_n": [
      "2486",
      "2345",
      "6781",
      "2330",
      "6451",
      "2891",
      "2383",
      "2404",
      "2357",
      "2454",
      "2308",
      "6919",
      "3231",
      "4958",
      "2455"
    ],
    "rejected_by_turnover": [
      "2481",
      "2485",
      "8021",
      "1309",
      "2355",
      "8271",
      "1717"
    ],
    "rejected_by_price": [
      "2344",
      "2409",
      "6770",
      "3481",
      "2485",
      "1309",
      "2489",
      "1802"
    ],
    "rejected_by_history": [
      "7769",
      "7822"
    ],
    "rejected_by_trend": [
      "2313",
      "3037",
      "2344",
      "2408",
      "8046",
      "2303",
      "6285",
      "2317",
      "2367",
      "1303",
      "2409",
      "2368",
      "2360",
      "6770",
      "3715",
      "6213",
      "3711",
      "8039",
      "2481",
      "3481",
      "2485",
      "3661",
      "2449",
      "8021",
      "3189",
      "3167",
      "3714",
      "6669",
      "8996",
      "2327",
      "6257",
      "3006",
      "4906",
      "8210",
      "2382",
      "6830",
      "6239",
      "3443",
      "1309",
      "2489",
      "2337",
      "2426",
      "1802",
      "2355",
      "8271",
      "2467",
      "4967",
      "1560",
      "1717",
      "6515",
      "6531",
      "6139",
      "1326",
      "2027"
    ],
    "rejected_by_industry": [],
    "positions": [
      {
        "symbol": "3450",
        "weight": 0.1168,
        "score": 88.82,
        "industry": "電子工業"
      },
      {
        "symbol": "6442",
        "weight": 0.1151,
        "score": 87.5,
        "industry": "通信網路業"
      },
      {
        "symbol": "6805",
        "weight": 0.1025,
        "score": 77.92,
        "industry": "電子零組件業"
      },
      {
        "symbol": "2059",
        "weight": 0.0964,
        "score": 73.33,
        "industry": "電子零組件業"
      },
      {
        "symbol": "3563",
        "weight": 0.0956,
        "score": 72.71,
        "industry": "電子工業"
      },
      {
        "symbol": "3665",
        "weight": 0.0929,
        "score": 70.62,
        "industry": "電子工業"
      },
      {
        "symbol": "3653",
        "weight": 0.0807,
        "score": 61.39,
        "industry": "電子零組件業"
      }
    ],
    "theme_concentration": {
      "tech_weight": 0.7,
      "tech_count": 7,
      "total_positions": 7,
      "top_industry": "電子工業",
      "top_industry_weight": 0.3053,
      "industries": {
        "電子工業": 0.3053,
        "電子零組件業": 0.2796,
        "通信網路業": 0.1151
      }
    },
    "factor_detail": [
      {
        "symbol": "3450",
        "rank": 1,
        "portfolio_score": 88.82,
        "rank_components": {
          "price_momentum": 95.83,
          "trend_quality": 62.5,
          "revenue_momentum": 94.44
        },
        "price_momentum_raw": 2.130532467532468,
        "trend_quality_raw": 0.7178,
        "revenue_raw": 0.6065608828472325,
        "institutional_raw": 0.0,
        "industry": "電子工業"
      },
      {
        "symbol": "6442",
        "rank": 2,
        "portfolio_score": 87.5,
        "rank_components": {
          "price_momentum": 100.0,
          "trend_quality": 100.0,
          "revenue_momentum": 50.0
        },
        "price_momentum_raw": 3.1839470139354287,
        "trend_quality_raw": 1.0,
        "revenue_raw": null,
        "institutional_raw": 0.0,
        "industry": "通信網路業"
      },
      {
        "symbol": "6805",
        "rank": 3,
        "portfolio_score": 77.92,
        "rank_components": {
          "price_momentum": 91.67,
          "trend_quality": 75.0,
          "revenue_momentum": 50.0
        },
        "price_momentum_raw": 1.185410340320362,
        "trend_quality_raw": 0.9374,
        "revenue_raw": null,
        "institutional_raw": 0.0,
        "industry": "電子零組件業"
      },
      {
        "symbol": "2059",
        "rank": 4,
        "portfolio_score": 73.33,
        "rank_components": {
          "price_momentum": 66.67,
          "trend_quality": 79.17,
          "revenue_momentum": 83.33
        },
        "price_momentum_raw": 0.5545483456795967,
        "trend_quality_raw": 0.9487,
        "revenue_raw": 0.39994040581964274,
        "institutional_raw": 0.0,
        "industry": "電子零組件業"
      },
      {
        "symbol": "3563",
        "rank": 5,
        "portfolio_score": 72.71,
        "rank_components": {
          "price_momentum": 62.5,
          "trend_quality": 66.67,
          "revenue_momentum": 100.0
        },
        "price_momentum_raw": 0.5539249941765665,
        "trend_quality_raw": 0.745,
        "revenue_raw": 0.8042343755564251,
        "institutional_raw": 0.0,
        "industry": "電子工業"
      },
      {
        "symbol": "3665",
        "rank": 6,
        "portfolio_score": 70.62,
        "rank_components": {
          "price_momentum": 87.5,
          "trend_quality": 91.67,
          "revenue_momentum": 16.67
        },
        "price_momentum_raw": 1.1700886405015296,
        "trend_quality_raw": 0.9655,
        "revenue_raw": 0.0763718842184101,
        "institutional_raw": 0.0,
        "industry": "電子工業"
      },
      {
        "symbol": "3533",
        "rank": 7,
        "portfolio_score": 69.24,
        "rank_components": {
          "price_momentum": 70.83,
          "trend_quality": 54.17,
          "revenue_momentum": 77.78
        },
        "price_momentum_raw": 0.6401596768556913,
        "trend_quality_raw": 0.6407,
        "revenue_raw": 0.28170850759388877,
        "institutional_raw": 0.0,
        "industry": "電子零組件業"
      },
      {
        "symbol": "3017",
        "rank": 8,
        "portfolio_score": 64.86,
        "rank_components": {
          "price_momentum": 75.0,
          "trend_quality": 41.67,
          "revenue_momentum": 61.11
        },
        "price_momentum_raw": 0.6420040160851609,
        "trend_quality_raw": 0.5732,
        "revenue_raw": 0.2435134940356971,
        "institutional_raw": 0.0,
        "industry": "電子工業"
      },
      {
        "symbol": "3653",
        "rank": 9,
        "portfolio_score": 61.39,
        "rank_components": {
          "price_momentum": 83.33,
          "trend_quality": 8.33,
          "revenue_momentum": 55.56
        },
        "price_momentum_raw": 0.9114056985017092,
        "trend_quality_raw": 0.3713,
        "revenue_raw": 0.2032825495255693,
        "institutional_raw": 0.0,
        "industry": "電子零組件業"
      },
      {
        "symbol": "2486",
        "rank": 10,
        "portfolio_score": 58.26,
        "rank_components": {
          "price_momentum": 79.17,
          "trend_quality": 45.83,
          "revenue_momentum": 22.22
        },
        "price_momentum_raw": 0.7538584321374217,
        "trend_quality_raw": 0.5902,
        "revenue_raw": 0.08559290949438107,
        "institutional_raw": 0.0,
        "industry": "電子工業"
      },
      {
        "symbol": "2345",
        "rank": 11,
        "portfolio_score": 54.93,
        "rank_components": {
          "price_momentum": 29.17,
          "trend_quality": 83.33,
          "revenue_momentum": 88.89
        },
        "price_momentum_raw": 0.28457087741471215,
        "trend_quality_raw": 0.961,
        "revenue_raw": 0.40969382312896724,
        "institutional_raw": 0.0,
        "industry": "電子工業"
      },
      {
        "symbol": "6781",
        "rank": 12,
        "portfolio_score": 54.17,
        "rank_components": {
          "price_momentum": 50.0,
          "trend_quality": 70.83,
          "revenue_momentum": 50.0
        },
        "price_momentum_raw": 0.47945177107435133,
        "trend_quality_raw": 0.7788,
        "revenue_raw": null,
        "institutional_raw": 0.0,
        "industry": "電子零組件業"
      },
      {
        "symbol": "2330",
        "rank": 13,
        "portfolio_score": 53.75,
        "rank_components": {
          "price_momentum": 58.33,
          "trend_quality": 25.0,
          "revenue_momentum": 66.67
        },
        "price_momentum_raw": 0.5333580345939772,
        "trend_quality_raw": 0.4289,
        "revenue_raw": 0.2573984245726719,
        "institutional_raw": 0.0,
        "industry": "電子工業"
      },
      {
        "symbol": "6451",
        "rank": 14,
        "portfolio_score": 49.79,
        "rank_components": {
          "price_momentum": 54.17,
          "trend_quality": 37.5,
          "revenue_momentum": 50.0
        },
        "price_momentum_raw": 0.5034912391891077,
        "trend_quality_raw": 0.5539,
        "revenue_raw": null,
        "institutional_raw": 0.0,
        "industry": "半導體業"
      },
      {
        "symbol": "2891",
        "rank": 15,
        "portfolio_score": 44.79,
        "rank_components": {
          "price_momentum": 37.5,
          "trend_quality": 58.33,
          "revenue_momentum": 50.0
        },
        "price_momentum_raw": 0.2902444923440041,
        "trend_quality_raw": 0.662,
        "revenue_raw": 0.19724619399826118,
        "institutional_raw": 0.0,
        "industry": "金融保險"
      },
      {
        "symbol": "2383",
        "rank": 16,
        "portfolio_score": 44.72,
        "rank_components": {
          "price_momentum": 16.67,
          "trend_quality": 87.5,
          "revenue_momentum": 72.22
        },
        "price_momentum_raw": 0.20675939050613207,
        "trend_quality_raw": 0.9646,
        "revenue_raw": 0.26114210499069473,
        "institutional_raw": 0.0,
        "industry": "電子零組件業"
      },
      {
        "symbol": "2404",
        "rank": 17,
        "portfolio_score": 43.47,
        "rank_components": {
          "price_momentum": 41.67,
          "trend_quality": 95.83,
          "revenue_momentum": 5.56
        },
        "price_momentum_raw": 0.425020764970422,
        "trend_quality_raw": 0.9713,
        "revenue_raw": -0.23697350619853497,
        "institutional_raw": 0.0,
        "industry": "電子工業"
      },
      {
        "symbol": "2357",
        "rank": 18,
        "portfolio_score": 40.76,
        "rank_components": {
          "price_momentum": 45.83,
          "trend_quality": 29.17,
          "revenue_momentum": 38.89
        },
        "price_momentum_raw": 0.46131850411229575,
        "trend_quality_raw": 0.4324,
        "revenue_raw": 0.1667311507694361,
        "institutional_raw": 0.0,
        "industry": "電腦及週邊設備業"
      },
      {
        "symbol": "2454",
        "rank": 19,
        "portfolio_score": 36.67,
        "rank_components": {
          "price_momentum": 33.33,
          "trend_quality": 50.0,
          "revenue_momentum": 33.33
        },
        "price_momentum_raw": 0.28758211587300747,
        "trend_quality_raw": 0.5959,
        "revenue_raw": 0.15064879697706596,
        "institutional_raw": 0.0,
        "industry": "電子工業"
      },
      {
        "symbol": "2308",
        "rank": 20,
        "portfolio_score": 27.36,
        "rank_components": {
          "price_momentum": 25.0,
          "trend_quality": 33.33,
          "revenue_momentum": 27.78
        },
        "price_momentum_raw": 0.2533666810662465,
        "trend_quality_raw": 0.5043,
        "revenue_raw": 0.1016114342017094,
        "institutional_raw": 0.0,
        "industry": "電子零組件業"
      }
    ],
    "config_hash": "3bb0d8efab1de820",
    "score_dispersion": {
      "std": 21.2976,
      "iqr": 29.8475,
      "n_eligible": 24
    }
  }
]